whoi_uwapm/__init__.py
whoi_uwapm/bellhop
whoi_uwapm/bellhopcxx
whoi_uwapm/uwapm.py
whoi_uwapm-0.0.4.dist-info/LICENSE
whoi_uwapm-0.0.4.dist-info/METADATA
whoi_uwapm-0.0.4.dist-info/WHEEL
whoi_uwapm-0.0.4.dist-info/top_level.txt
whoi_uwapm-0.0.4.dist-info/RECORD
