Metadata-Version: 2.1
Name: whoi-uwapm
Version: 0.0.4
Summary: WHOI Acomms Group uwapm
Home-page: https://git.whoi.edu/acomms/whoi_uwapm
Author: WHOI Acomms Group
License: BSD (3-clause)
License-File: LICENSE
Requires-Dist: numpy
Requires-Dist: pandas
Requires-Dist: scipy
